{"trial_id": "00", "hyperparameters": {"space": [{"class_name": "Int", "config": {"name": "units_input", "default": null, "conditions": [], "min_value": 32, "max_value": 256, "step": 32, "sampling": "linear"}}, {"class_name": "Float", "config": {"name": "dropout_1", "default": 0.0, "conditions": [], "min_value": 0.0, "max_value": 0.5, "step": 0.1, "sampling": "linear"}}, {"class_name": "Int", "config": {"name": "units_hidden", "default": null, "conditions": [], "min_value": 32, "max_value": 256, "step": 32, "sampling": "linear"}}, {"class_name": "Float", "config": {"name": "dropout_2", "default": 0.0, "conditions": [], "min_value": 0.0, "max_value": 0.5, "step": 0.1, "sampling": "linear"}}, {"class_name": "Float", "config": {"name": "learning_rate", "default": 0.0001, "conditions": [], "min_value": 0.0001, "max_value": 0.01, "step": null, "sampling": "log"}}], "values": {"units_input": 160, "dropout_1": 0.1, "units_hidden": 160, "dropout_2": 0.0, "learning_rate": 0.0012502824673384133}}, "metrics": {"metrics": {"loss": {"direction": "min", "observations": [{"value": [0.0021571177639998496], "step": 5}]}, "mean_absolute_error": {"direction": "min", "observations": [{"value": [0.03451736271381378], "step": 5}]}, "val_loss": {"direction": "min", "observations": [{"value": [0.0005099544214317575], "step": 5}]}, "val_mean_absolute_error": {"direction": "min", "observations": [{"value": [0.017839761450886726], "step": 5}]}}}, "score": 0.017839761450886726, "best_step": 5, "status": "COMPLETED", "message": null}